  public int sum(scala.collection.immutable.List<java.lang.Object>);
    Code:
       0: aload_1
       1: invokevirtual #63                 // Method scala/collection/immutable/List.isEmpty:()Z
       4: ifeq          11
       7: iconst_0
       8: goto          30
      11: aload_1
      12: invokevirtual #67                 // Method scala/collection/immutable/List.head:()Ljava/lang/Object;
      15: invokestatic  #73                 // Method scala/runtime/BoxesRunTime.unboxToInt:(Ljava/lang/Object;)I
      18: aload_0
      19: aload_1
      20: invokevirtual #76                 // Method scala/collection/immutable/List.tail:()Ljava/lang/Object;
      23: checkcast     #59                 // class scala/collection/immutable/List
      26: invokevirtual #78                 // Method sum:(Lscala/collection/immutable/List;)I
      29: iadd
      30: ireturn
