Compiled from ""Animal.scala""
public class Cat implements Animal {
  public void speak();
    Code:
       0: getstatic     #18                 // Field scala/Predef$.MODULE$:Lscala/Predef$;
       3: ldc           #20                 // String meow....
       5: invokevirtual #24                 // Method scala/Predef$.println:(Ljava/lang/Object;)V
       8: return

  public void comeToMaster();
    Code:
       0: getstatic     #18                 // Field scala/Predef$.MODULE$:Lscala/Predef$;
       3: ldc           #29                 // String catch me if you can..
       5: invokevirtual #24                 // Method scala/Predef$.println:(Ljava/lang/Object;)V
       8: return

  public Cat();
    Code:
       0: aload_0
       1: invokespecial #32                 // Method java/lang/Object.""<init>"":()V
       4: aload_0
       5: invokestatic  #36                 // InterfaceMethod Animal.$init$:(LAnimal;)V
       8: return
}
