Compiled from "Animal.scala"
public interface Animal {
  public static void speak$(Animal);
    Code:
       0: aload_0
       1: invokespecial #15                 // InterfaceMethod speak:()V
       4: return

  public void speak();
    Code:
       0: getstatic     #22                 // Field scala/Predef$.MODULE$:Lscala/Predef$;
       3: ldc           #24                 // String speaking..
       5: invokevirtual #28                 // Method scala/Predef$.println:(Ljava/lang/Object;)V
       8: return

  public abstract void comeToMaster();

  public static void $init$(Animal);
    Code:
       0: return
}
